setup.py
cepwebservice/__init__.py
cepwebservice/conf.py
cepwebservice/constants.py
cepwebservice/models.py
cepwebservice/urls.py
cepwebservice/utils.py
cepwebservice/version.py
cepwebservice/views.py
django_cepwebservice.egg-info/PKG-INFO
django_cepwebservice.egg-info/SOURCES.txt
django_cepwebservice.egg-info/dependency_links.txt
django_cepwebservice.egg-info/top_level.txt