Metadata-Version: 1.1
Name: django-cepwebservice
Version: 0.0.1
Summary: WebService de CEP para Django.
Home-page: https://github.com/adonescunha/django-cepwebservice
Author: Adones Cunha
Author-email: adonescunha@gmail.com
License: UNKNOWN
Platform: UNKNOWN
Classifier: Development Status :: 1 - Planning
Classifier: Environment :: Web Environment
Classifier: Intended Audience :: Developers
Classifier: License :: OSI Approved :: MIT License
Classifier: Natural Language :: English
Classifier: Operating System :: OS Independent
Classifier: Programming Language :: Python
Classifier: Framework :: Django
